flip-flop/design.v
module D_flip_flop(res,Clk,D,Q);

    input res, Clk, D;
    output reg Q;

    always @(posedge Clk) begin
      if(res == 1'b1) begin
        Q <= 1'b0;
      end
      else begin
        Q <= D;
      end
    end

endmodule

flip-flop/testbench.v
module tb();

    reg res, Clk, D;

    wire Q;

    D_flip_flop dut (
        .res(res),
        .Clk(Clk),
        .D(D),
        .Q(Q)
    );

    always begin
      Clk <= 1'b0;
      #50;
      Clk <= 1'b1;
      #50;
    end

    initial begin
      
      res <= 1'b1;
      #100;
      res <= 1'b0;
      #100;
      D <= 1'b1;
      #100;
      D <= 1'b0;
      #100;
      $finish;

    end

    initial begin
      $dumpfile("dump.vcd");
      $dumpvars(0);
    end

endmodule

flip-flop/dump.vcd
$date
	Sun Sep 21 10:40:21 2025
$end
$version
	Icarus Verilog
$end
$timescale
	1s
$end
$scope module tb $end
$var wire 1 ! Q $end
$var reg 1 " Clk $end
$var reg 1 # D $end
$var reg 1 $ res $end
$scope module dut $end
$var wire 1 " Clk $end
$var wire 1 # D $end
$var wire 1 $ res $end
$var reg 1 ! Q $end
$upscope $end
$upscope $end
$enddefinitions $end
$comment Show the parameter values. $end
$dumpall
$end
#0
$dumpvars
1$
x#
0"
x!
$end
#50
0!
1"
#100
0"
0$
#150
x!
1"
#200
0"
1#
#250
1!
1"
#300
0"
0#
#350
0!
1"
